{
  "prefecture_code": "33",
  "prefecture_name": "岡山県",
  "district_number": 3,
  "district_name": "岡山3区",
  "status": "completed",
  "is_official": true,
  "last_updated": "2026-01-29T21:00:22+09:00",
  "total_candidates": 2,
  "processed_candidates": 2,
  "candidates": [
    {
      "name": "加藤勝信",
      "name_kana": "かとうかつのぶ",
      "age": 70,
      "party": "自由民主党",
      "status": "前職",
      "proportional_rank": null,
      "processing": {
        "researched": true,
        "evaluated": true,
        "md_created": true,
        "card_generated": false
      }
    },
    {
      "name": "原田亜希子",
      "name_kana": "はらだあきこ",
      "age": 53,
      "party": "日本共産党",
      "status": "新人",
      "proportional_rank": null,
      "processing": {
        "researched": true,
        "evaluated": true,
        "md_created": true,
        "card_generated": false
      }
    }
  ]
}
