{
  "prefecture_code": "38",
  "prefecture_name": "愛媛県",
  "district_number": 1,
  "district_name": "愛媛1区",
  "status": "completed",
  "is_official": true,
  "last_updated": "2026-01-29T19:19:33+09:00",
  "total_candidates": 4,
  "processed_candidates": 4,
  "candidates": [
    {
      "name": "塩崎彰久",
      "name_kana": "しおざき あきひさ",
      "age": 49,
      "party": "自由民主党",
      "status": "前職",
      "proportional_rank": null,
      "processing": {
        "researched": true,
        "evaluated": true,
        "md_created": true,
        "card_generated": false
      }
    },
    {
      "name": "石井智恵",
      "name_kana": "いしい ちえ",
      "age": 58,
      "party": "国民民主党",
      "status": "前職",
      "proportional_rank": null,
      "processing": {
        "researched": true,
        "evaluated": true,
        "md_created": true,
        "card_generated": false
      }
    },
    {
      "name": "和田宰",
      "name_kana": "わだ さい",
      "age": 73,
      "party": "日本共産党",
      "status": "新人",
      "proportional_rank": null,
      "processing": {
        "researched": true,
        "evaluated": true,
        "md_created": true,
        "card_generated": false
      }
    },
    {
      "name": "篠藤愛",
      "name_kana": "しのとう あい",
      "age": 36,
      "party": "参政党",
      "status": "新人",
      "proportional_rank": null,
      "processing": {
        "researched": true,
        "evaluated": true,
        "md_created": true,
        "card_generated": false
      }
    }
  ]
}
